FizzMath/SimpleCal.py
FizzMath/__init__.py
FizzMath-0.0.1.dist-info/LICENSE
FizzMath-0.0.1.dist-info/METADATA
FizzMath-0.0.1.dist-info/WHEEL
FizzMath-0.0.1.dist-info/top_level.txt
FizzMath-0.0.1.dist-info/RECORD
