Metadata-Version: 2.1
Name: FizzMath
Version: 0.0.1
Summary: A testing lib
Home-page: https://github.com/fizz-whu/FizzMath
Author: Chee Fan
Author-email: fizz.job@gmail.com
License: UNKNOWN
Platform: UNKNOWN
Classifier: Programming Language :: Python :: 3
Classifier: License :: OSI Approved :: MIT License
Classifier: Operating System :: OS Independent
Requires-Python: >=3.6
